vibe_llama_core/__init__.py
vibe_llama_core/constants.py
vibe_llama_core/docs/__init__.py
vibe_llama_core/docs/data.py
vibe_llama_core/docs/utils.py
vibe_llama_core/templates/__init__.py
vibe_llama_core/templates/scaffold.py
vibe_llama_core-0.2.1.dist-info/METADATA
vibe_llama_core-0.2.1.dist-info/WHEEL
vibe_llama_core-0.2.1.dist-info/RECORD
