Metadata-Version: 2.4
Name: vibe-llama-core
Version: 0.2.1
Summary: vibe-llama-core is a reduced version of vibe-llama containing only the code for downloading documentation and templates.
Requires-Python: >=3.10
Requires-Dist: copier>=9.10.2
Requires-Dist: httpx<1,>=0.28.1
